docker_machine_add_ssh.py
docker_machine_add_ssh-1.9.dist-info/METADATA
docker_machine_add_ssh-1.9.dist-info/WHEEL
docker_machine_add_ssh-1.9.dist-info/entry_points.txt
docker_machine_add_ssh-1.9.dist-info/top_level.txt
docker_machine_add_ssh-1.9.dist-info/RECORD
