Metadata-Version: 2.4
Name: docker-machine-add-ssh
Version: 1.9
Summary: Adds docker-machine ssh configuration into your personal ssh configuration
Author-email: Mark Blakeney <mark.blakeney@bullet-systems.net>
License-Expression: GPL-3.0-or-later
Project-URL: Homepage, https://github.com/bulletmark/docker-machine-add-ssh
Keywords: docker,docker-machine,ssh
Classifier: Programming Language :: Python :: 3
Requires-Python: >=3.8
Requires-Dist: argparse-from-file
